webhook_listener/__init__.py
webhook_listener/version.py
Webhook_Listener-1.2.0.dist-info/LICENSE
Webhook_Listener-1.2.0.dist-info/METADATA
Webhook_Listener-1.2.0.dist-info/WHEEL
Webhook_Listener-1.2.0.dist-info/top_level.txt
Webhook_Listener-1.2.0.dist-info/RECORD
