Metadata-Version: 2.1
Name: Webhook-Listener
Version: 1.2.0
Summary: Very basic webserver module to listen for webhooks and forward requests to predefined functions.
Home-page: https://github.com/toddrob99/Webhooks
Author: Todd Roberts
Author-email: todd@toddrob.com
License: UNKNOWN
Platform: UNKNOWN
Classifier: Programming Language :: Python
Classifier: Programming Language :: Python :: 3
Classifier: License :: OSI Approved :: MIT License
Classifier: Operating System :: OS Independent
License-File: LICENSE
Requires-Dist: cherrypy
